jsonflat/__init__.py
jsonflat/field.py
jsonflat/jsonflat.py
tests/__init__.py
tests/test_field.py
tests/test_jsonflat.py
json_flat-1.0.0.dist-info/LICENSE
json_flat-1.0.0.dist-info/METADATA
json_flat-1.0.0.dist-info/WHEEL
json_flat-1.0.0.dist-info/top_level.txt
json_flat-1.0.0.dist-info/RECORD
