Metadata-Version: 2.1
Name: json-flat
Version: 1.0.0
Summary: A Python library to flatten a nested json
Home-page: https://github.com/vivek-shrikhande/json-flat
Author: Vivek Shrikhande
Author-email: vivekshrikhande444@gmail.com
License: UNKNOWN
Platform: UNKNOWN
Classifier: Programming Language :: Python :: 3.6
Classifier: Programming Language :: Python :: 3.7
Classifier: Programming Language :: Python :: 3.8
Classifier: License :: OSI Approved :: MIT License
Classifier: Operating System :: OS Independent
Requires-Python: ~=3.6
